tenyks/__init__.py
tenyks/__main__.py
tenyks/api.py
tenyks/cli.py
tenyks/click_utilities.py
tenyks/exceptions_handler.py
tenyks/upload_utilities.py
tenyks/utilities.py
tenyks/adapters/__init__.py
tenyks/adapters/config.py
tenyks/adapters/categories/__init__.py
tenyks/adapters/categories/category_reader_factory.py
tenyks/adapters/categories/readers/__init__.py
tenyks/adapters/categories/readers/category_reader.py
tenyks/adapters/categories/readers/json_category_reader.py
tenyks/adapters/categories/readers/txt_category_reader.py
tenyks/adapters/detection/__init__.py
tenyks/adapters/detection/detection_adapter.py
tenyks/adapters/detection/detection_adapter_factory.py
tenyks/adapters/detection/detection_data.py
tenyks/adapters/detection/readers/__init__.py
tenyks/adapters/detection/readers/classification_reader.py
tenyks/adapters/detection/readers/deepstream_reader.py
tenyks/adapters/detection/readers/detection_reader.py
tenyks/adapters/detection/readers/vott_csv_reader.py
tenyks/adapters/detection/readers/yolo_reader.py
tenyks/adapters/detection/writers/__init__.py
tenyks/adapters/detection/writers/coco_writer.py
tenyks/adapters/detection/writers/detection_writer.py
tenyks/adapters/utilities/__init__.py
tenyks/adapters/utilities/bbox.py
tenyks/adapters/utilities/file.py
tenyks/config/__init__.py
tenyks/config/config.py
tenyks/config/configure.py
tenyks/config/providers/__init__.py
tenyks/config/providers/aws/__init__.py
tenyks/config/providers/aws/config_aws.py
tenyks/config/providers/aws/configure_aws.py
tenyks/convert/__init__.py
tenyks/convert/convert_detections_file.py
tenyks/convert/detection_file_processor.py
tenyks/dataset/__init__.py
tenyks/dataset/config.py
tenyks/dataset/create_dataset.py
tenyks/dataset/upload_annotations.py
tenyks/dataset/upload_class_names.py
tenyks/dataset/upload_images.py
tenyks/dataset/utilities.py
tenyks/dataset/aws/__init__.py
tenyks/dataset/aws/dataclasses.py
tenyks/embeddings/__init__.py
tenyks_cli-0.2.51.dist-info/METADATA
tenyks_cli-0.2.51.dist-info/WHEEL
tenyks_cli-0.2.51.dist-info/entry_points.txt
tenyks_cli-0.2.51.dist-info/top_level.txt
tenyks_cli-0.2.51.dist-info/RECORD
