Metadata-Version: 2.1
Name: tenyks-cli
Version: 0.2.51
Summary: Tenyks AI
Home-page: https://www.tenyks.ai/
Author: Tenyks AI
Author-email: info@tenyks.ai
License: MIT
Classifier: Programming Language :: Python :: 3.8
Classifier: License :: OSI Approved :: MIT License
Classifier: Operating System :: OS Independent
Requires-Python: >=3.7
Requires-Dist: click
Requires-Dist: requests
Requires-Dist: aiohttp
Requires-Dist: pandas
Requires-Dist: dataclasses-json
Requires-Dist: Pillow
